pith/__init__.py
pith/app.py
pith/command.py
pith/compat.py
pith/decorators.py
pith/discovery.py
pith/parameters.py
pith/parsing.py
pith/py.typed
pith/testing.py
pith/utils.py
pith/core/__init__.py
pith/core/hints.py
pith/core/py.typed
pith/core/render.py
pith/core/run_line.py
pith/core/schema.py
pith/core/search.py
pith/core/types.py
pypith-0.1.2.dist-info/METADATA
pypith-0.1.2.dist-info/WHEEL
pypith-0.1.2.dist-info/RECORD
