Metadata-Version: 2.4
Name: pypith
Version: 0.1.2
Summary: Build agent-native Python CLIs with progressive discovery
Project-URL: Homepage, https://github.com/ThomasRohde/pith
Project-URL: Repository, https://github.com/ThomasRohde/pith
Project-URL: Documentation, https://github.com/ThomasRohde/pith#readme
Project-URL: Changelog, https://github.com/ThomasRohde/pith/releases
Author-email: Thomas Klok Rohde <rohde.thomas@gmail.com>
License-Expression: MIT
Keywords: agent,ai,cli,command-line,llm,progressive-discovery,typer-alternative
Classifier: Development Status :: 3 - Alpha
Classifier: Environment :: Console
Classifier: Intended Audience :: Developers
Classifier: License :: OSI Approved :: MIT License
Classifier: Programming Language :: Python :: 3
Classifier: Programming Language :: Python :: 3.10
Classifier: Programming Language :: Python :: 3.11
Classifier: Programming Language :: Python :: 3.12
Classifier: Programming Language :: Python :: 3.13
Classifier: Topic :: Software Development :: Libraries :: Python Modules
Classifier: Topic :: System :: Shells
Classifier: Typing :: Typed
Requires-Python: >=3.10
Provides-Extra: rich
Requires-Dist: rich>=13.0; extra == 'rich'
Provides-Extra: semantic
Requires-Dist: sentence-transformers>=2.2; extra == 'semantic'
